Workbook
Name Slicer_Is_Weekend_or_BH: #N/A
Name Slicer_Month_Filter: #N/A
Name Slicer_Year_Filter: #N/A

Sheet Readme
B2: 🥩 Weather-Driven FMCG Supply Chain & Margin Analytics
B4: 📌 Project Overview
B5: This commercial-grade data analytics project explores the correlation between weather conditions (daily temperature fluctuations/extreme rain) and FMCG operations in Gloucestershire, UK. The project transitions raw operational data into actionable business insights to optimize inventory levels, eliminate waste, and protect financial margins during weather anomalies.
B9: 📊 Key Business Insights & Analytical Framework (From the Report):
B11: 1. Data Quality Assessment (DQA): Audited and cleaned a historical dataset of 300 daily records (2023–2026) using Power Query, standardizing calendar tags, handling empty financial rows, and creating conditional attributes for Extreme Heat ($>30^\circ\text{C}$).
B12: 2. The "Ruined Weekend Effect" (Bank Holiday Analysis): Quantified baseline financial losses from supply chain pre-allocation during extreme weather.
B13: Extreme Heat Bank Holiday: Generates an average loss of £1,258.00/day in wasted meat stock.
B14: Heavy Rain Bank Holiday: Generates an average loss of £1,124.80/day.
B15: Standard Sunny Weekends incur £0.00 in weather-related spoilage.
B16: 3. Market Basket Shift (Mirror Effect): Demonstrated that consumer demand during heatwaves shifts from meat to refreshments:
B17: Meat Demand (Beef & Pork): -85%
B18: Bagged Ice Demand: +450% | Ice Cream: +310% | Soft Drinks: +240%
... B34: Focus: Data Analytics | Supply Chain Logistics | FMCG Operations

Sheet Change_Log
A1: Stage | B1: Version | C1: Date | D1: Module / Functionality | E1: Description of Changes | F1: Status
A2: Stage 1: Ingestion | B2: v0.1 | C2: 46204 | D2: Web Data Ingestion | E2: Set up automatic data import from external websites (temperature table import, pork and beef procurement and sales volumes import ). | F2: Completed
A3: Stage 2: Cleaning | B3: v0.2 | C3: 46206 | D3: Data Cleaning & Parsing | E3: Developed a "raw" data cleaning algorithm: text splitting via TEXTSPLIT, duplicate removal, and handling empty values using pad_with = "". | F3: Completed
A4: Stage 3: Modeling | B4: v1.0 | C4: 46208 | D4: Temperature Matrix | E4: Formed the main temperature calculation table. Integrated XLOOKUP functions for reverse lookup of the latest values and date handling. | F4: Completed
A5: Stage 3: Modeling | B5: v1.1 | C5: 46209 | D5: Data Aggregation | E5: Set up analytical formulas (SUMIFS, COUNTIFS) and dynamic sorting via SORTBY for data grouping. | F5: Completed
A6: Stage 4: Presentation | B6: v1.2 | C6: Current | D6: Dashboard & UI | E6: Creating the final dashboard with charts, configuring the cell color code, and drafting instructions on the Readme sheet. | F6: Completed

Sheet Resource links
B1: Resource links
A2: 1 | B2: Beef Market Trends & Dynamics | C2: Inputs / Market_Analysis | D2: Monthly | E2: AHDB Beef Markets
A3: 2 | B3: Meat Consumption & Industry Facts | C3: Readme / Assumptions | D3: Annually | E3: Food Foundation Meat Facts
A4: 3 | B4: Regional Weather Data (Gloucester) | C4: Temperature_Matrix | D4: Daily / Weekly | E4: Meteostat Gloucester Weather
A5: 4 | B5: GB Deadweight Cattle Prices | C5: Calculations / Pricing | D5: Weekly | E5: AHDB Deadweight Cattle Prices

Sheet Project clean data
A1: Date | B1: Is_Weekend_or_BH | C1: Max_Temperature_C | D1: Rainfall_mm | E1: Beef_Historical_Order_kg | F1: Beef_Actual_Sales_kg | G1: Beef_Wasted_Stock_kg | H1: Beef_Financial_Loss_£ | I1: Pork_Historical_Order_kg | J1: Pork_Actual_Sales_kg | K1: Pork_Wasted_Stock_kg | L1: Pork_Financial_Loss_£ | M1: Weather_Condition | N1: Year_Filter | O1: Month_Filter
A2: 45047 | B2: YES | C2: =_xlfn.XLOOKUP(A2,Weather_clean_data!A:A,Weather_clean_data!B:B,0) -> 18 | D2: =_xlfn.XLOOKUP(A2, Weather_clean_data!A:A, Weather_clean_data!C:C, 0) -> 1.3 | E2: =IF(B2="Yes", 150, 60) -> 150 | F2: =IF(C2>30,E2*0.15,IF(D2>5,IF(B2="YES",36,18),E2)) -> 150 | G2: =E2-F2 -> 0 | H2: =G2 * 7.2 -> 0 | I2: =IF(B2="Yes", 100, 40) -> 100 | J2: =IF(C2>30,I2*0.15,IF(D2>5,IF(B2="YES",24,12),I2)) -> 100 | K2: =I2-J2 -> 0 | L2: =K2 * 4 -> 0 | M2: Ideal BBQ Day | N2: 2023 | O2: May
A3: 45048 | B3: =IF( WEEKDAY(A3, 2) > 5, "YES", "NO") -> NO | C3: =_xlfn.XLOOKUP(A3,Weather_clean_data!A:A,Weather_clean_data!B:B,0) -> 17 | D3: =_xlfn.XLOOKUP(A3, Weather_clean_data!A:A, Weather_clean_data!C:C, 0) -> 0.1 | E3: =IF(B3="Yes", 150, 60) -> 60 | F3: =IF(C3>30,E3*0.15,IF(D3>5,IF(B3="YES",36,18),E3)) -> 60 | G3: =E3-F3 -> 0 | H3: =G3 * 7.2 -> 0 | I3: =IF(B3="Yes", 100, 40) -> 40 | J3: =IF(C3>30,I3*0.15,IF(D3>5,IF(B3="YES",24,12),I3)) -> 40 | K3: =I3-J3 -> 0 | L3: =K3 * 4 -> 0 | M3: Normal Weekday | N3: 2023 | O3: May
A4: 45049 | B4: =IF( WEEKDAY(A4, 2) > 5, "YES", "NO") -> NO | C4: =_xlfn.XLOOKUP(A4,Weather_clean_data!A:A,Weather_clean_data!B:B,0) -> 16 | D4: =_xlfn.XLOOKUP(A4, Weather_clean_data!A:A, Weather_clean_data!C:C, 0) -> 0 | E4: =IF(B4="Yes", 150, 60) -> 60 | F4: =IF(C4>30,E4*0.15,IF(D4>5,IF(B4="YES",36,18),E4)) -> 60 | G4: =E4-F4 -> 0 | H4: =G4 * 7.2 -> 0 | I4: =IF(B4="Yes", 100, 40) -> 40 | J4: =IF(C4>30,I4*0.15,IF(D4>5,IF(B4="YES",24,12),I4)) -> 40 | K4: =I4-J4 -> 0 | L4: =K4 * 4 -> 0 | M4: Normal Weekday | N4: 2023 | O4: May
A5: 45050 | B5: =IF( WEEKDAY(A5, 2) > 5, "YES", "NO") -> NO | C5: =_xlfn.XLOOKUP(A5,Weather_clean_data!A:A,Weather_clean_data!B:B,0) -> 18 | D5: =_xlfn.XLOOKUP(A5, Weather_clean_data!A:A, Weather_clean_data!C:C, 0) -> 1.9 | E5: =IF(B5="Yes", 150, 60) -> 60 | F5: =IF(C5>30,E5*0.15,IF(D5>5,IF(B5="YES",36,18),E5)) -> 60 | G5: =E5-F5 -> 0 | H5: =G5 * 7.2 -> 0 | I5: =IF(B5="Yes", 100, 40) -> 40 | J5: =IF(C5>30,I5*0.15,IF(D5>5,IF(B5="YES",24,12),I5)) -> 40 | K5: =I5-J5 -> 0 | L5: =K5 * 4 -> 0 | M5: Normal Weekday | N5: 2023 | O5: May
A6: 45051 | B6: =IF( WEEKDAY(A6, 2) > 5, "YES", "NO") -> NO | C6: =_xlfn.XLOOKUP(A6,Weather_clean_data!A:A,Weather_clean_data!B:B,0) -> 18 | D6: =_xlfn.XLOOKUP(A6, Weather_clean_data!A:A, Weather_clean_data!C:C, 0) -> 2.5 | E6: =IF(B6="Yes", 150, 60) -> 60 | F6: =IF(C6>30,E6*0.15,IF(D6>5,IF(B6="YES",36,18),E6)) -> 60 | G6: =E6-F6 -> 0 | H6: =G6 * 7.2 -> 0 | I6: =IF(B6="Yes", 100, 40) -> 40 | J6: =IF(C6>30,I6*0.15,IF(D6>5,IF(B6="YES",24,12),I6)) -> 40 | K6: =I6-J6 -> 0 | L6: =K6 * 4 -> 0 | M6: Ideal BBQ Day | N6: 2023 | O6: May
A7: 45052 | B7: =IF( WEEKDAY(A7, 2) > 5, "YES", "NO") -> YES | C7: =_xlfn.XLOOKUP(A7,Weather_clean_data!A:A,Weather_clean_data!B:B,0) -> 16 | D7: =_xlfn.XLOOKUP(A7, Weather_clean_data!A:A, Weather_clean_data!C:C, 0) -> 2.3 | E7: =IF(B7="Yes", 150, 60) -> 150 | F7: =IF(C7>30,E7*0.15,IF(D7>5,IF(B7="YES",36,18),E7)) -> 150 | G7: =E7-F7 -> 0 | H7: =G7 * 7.2 -> 0 | I7: =IF(B7="Yes", 100, 40) -> 100 | J7: =IF(C7>30,I7*0.15,IF(D7>5,IF(B7="YES",24,12),I7)) -> 100 | K7: =I7-J7 -> 0 | L7: =K7 * 4 -> 0 | M7: Ideal BBQ Day | N7: 2023 | O7: May
A8: 45053 | B8: =IF( WEEKDAY(A8, 2) > 5, "YES", "NO") -> YES | C8: =_xlfn.XLOOKUP(A8,Weather_clean_data!A:A,Weather_clean_data!B:B,0) -> 19 | D8: =_xlfn.XLOOKUP(A8, Weather_clean_data!A:A, Weather_clean_data!C:C, 0) -> 0 | E8: =IF(B8="Yes", 150, 60) -> 150 | F8: =IF(C8>30,E8*0.15,IF(D8>5,IF(B8="YES",36,18),E8)) -> 150 | G8: =E8-F8 -> 0 | H8: =G8 * 7.2 -> 0 | I8: =IF(B8="Yes", 100, 40) -> 100 | J8: =IF(C8>30,I8*0.15,IF(D8>5,IF(B8="YES",24,12),I8)) -> 100 | K8: =I8-J8 -> 0 | L8: =K8 * 4 -> 0 | M8: Ideal BBQ Day | N8: 2023 | O8: May
A9: 45054 | B9: YES | C9: =_xlfn.XLOOKUP(A9,Weather_clean_data!A:A,Weather_clean_data!B:B,0) -> 16 | D9: =_xlfn.XLOOKUP(A9, Weather_clean_data!A:A, Weather_clean_data!C:C, 0) -> 9.3 | E9: =IF(B9="Yes", 150, 60) -> 150 | F9: =IF(C9>30,E9*0.15,IF(D9>5,IF(B9="YES",36,18),E9)) -> 36 | G9: =E9-F9 -> 114 | H9: =G9 * 7.2 -> 820.8 | I9: =IF(B9="Yes", 100, 40) -> 100 | J9: =IF(C9>30,I9*0.15,IF(D9>5,IF(B9="YES",24,12),I9)) -> 24 | K9: =I9-J9 -> 76 | L9: =K9 * 4 -> 304 | M9: Heavy Rain | N9: 2023 | O9: May
A10: 45055 | B10: =IF( WEEKDAY(A10, 2) > 5, "YES", "NO") -> NO | C10: =_xlfn.XLOOKUP(A10,Weather_clean_data!A:A,Weather_clean_data!B:B,0) -> 18 | D10: =_xlfn.XLOOKUP(A10, Weather_clean_data!A:A, Weather_clean_data!C:C, 0) -> 10.2 | E10: =IF(B10="Yes", 150, 60) -> 60 | F10: =IF(C10>30,E10*0.15,IF(D10>5,IF(B10="YES",36,18),E10)) -> 18 | G10: =E10-F10 -> 42 | H10: =G10 * 7.2 -> 302.4 | I10: =IF(B10="Yes", 100, 40) -> 40 | J10: =IF(C10>30,I10*0.15,IF(D10>5,IF(B10="YES",24,12),I10)) -> 12 | K10: =I10-J10 -> 28 | L10: =K10 * 4 -> 112 | M10: Heavy Rain | N10: 2023 | O10: May
A11: 45056 | B11: =IF( WEEKDAY(A11, 2) > 5, "YES", "NO") -> NO | C11: =_xlfn.XLOOKUP(A11,Weather_clean_data!A:A,Weather_clean_data!B:B,0) -> 16 | D11: =_xlfn.XLOOKUP(A11, Weather_clean_data!A:A, Weather_clean_data!C:C, 0) -> 3.2 | E11: =IF(B11="Yes", 150, 60) -> 60 | F11: =IF(C11>30,E11*0.15,IF(D11>5,IF(B11="YES",36,18),E11)) -> 60 | G11: =E11-F11 -> 0 | H11: =G11 * 7.2 -> 0 | I11: =IF(B11="Yes", 100, 40) -> 40 | J11: =IF(C11>30,I11*0.15,IF(D11>5,IF(B11="YES",24,12),I11)) -> 40 | K11: =I11-J11 -> 0 | L11: =K11 * 4 -> 0 | M11: Normal Weekday | N11: 2023 | O11: May
A12: 45057 | B12: =IF( WEEKDAY(A12, 2) > 5, "YES", "NO") -> NO | C12: =_xlfn.XLOOKUP(A12,Weather_clean_data!A:A,Weather_clean_data!B:B,0) -> 19 | D12: =_xlfn.XLOOKUP(A12, Weather_clean_data!A:A, Weather_clean_data!C:C, 0) -> 0.4 | E12: =IF(B12="Yes", 150, 60) -> 60 | F12: =IF(C12>30,E12*0.15,IF(D12>5,IF(B12="YES",36,18),E12)) -> 60 | G12: =E12-F12 -> 0 | H12: =G12 * 7.2 -> 0 | I12: =IF(B12="Yes", 100, 40) -> 40 | J12: =IF(C12>30,I12*0.15,IF(D12>5,IF(B12="YES",24,12),I12)) -> 40 | K12: =I12-J12 -> 0 | L12: =K12 * 4 -> 0 | M12: Normal Weekday | N12: 2023 | O12: May
A13: 45058 | B13: =IF( WEEKDAY(A13, 2) > 5, "YES", "NO") -> NO | C13: =_xlfn.XLOOKUP(A13,Weather_clean_data!A:A,Weather_clean_data!B:B,0) -> 15 | D13: =_xlfn.XLOOKUP(A13, Weather_clean_data!A:A, Weather_clean_data!C:C, 0) -> 0.1 | E13: =IF(B13="Yes", 150, 60) -> 60 | F13: =IF(C13>30,E13*0.15,IF(D13>5,IF(B13="YES",36,18),E13)) -> 60 | G13: =E13-F13 -> 0 | H13: =G13 * 7.2 -> 0 | I13: =IF(B13="Yes", 100, 40) -> 40 | J13: =IF(C13>30,I13*0.15,IF(D13>5,IF(B13="YES",24,12),I13)) -> 40 | K13: =I13-J13 -> 0 | L13: =K13 * 4 -> 0 | M13: Ideal BBQ Day | N13: 2023 | O13: May
A14: 45059 | B14: =IF( WEEKDAY(A14, 2) > 5, "YES", "NO") -> YES | C14: =_xlfn.XLOOKUP(A14,Weather_clean_data!A:A,Weather_clean_data!B:B,0) -> 16 | D14: =_xlfn.XLOOKUP(A14, Weather_clean_data!A:A, Weather_clean_data!C:C, 0) -> 0 | E14: =IF(B14="Yes", 150, 60) -> 150 | F14: =IF(C14>30,E14*0.15,IF(D14>5,IF(B14="YES",36,18),E14)) -> 150 | G14: =E14-F14 -> 0 | H14: =G14 * 7.2 -> 0 | I14: =IF(B14="Yes", 100, 40) -> 100 | J14: =IF(C14>30,I14*0.15,IF(D14>5,IF(B14="YES",24,12),I14)) -> 100 | K14: =I14-J14 -> 0 | L14: =K14 * 4 -> 0 | M14: Ideal BBQ Day | N14: 2023 | O14: May
A15: 45060 | B15: =IF( WEEKDAY(A15, 2) > 5, "YES", "NO") -> YES | C15: =_xlfn.XLOOKUP(A15,Weather_clean_data!A:A,Weather_clean_data!B:B,0) -> 18.6 | D15: =_xlfn.XLOOKUP(A15, Weather_clean_data!A:A, Weather_clean_data!C:C, 0) -> 0.7 | E15: =IF(B15="Yes", 150, 60) -> 150 | F15: =IF(C15>30,E15*0.15,IF(D15>5,IF(B15="YES",36,18),E15)) -> 150 | G15: =E15-F15 -> 0 | H15: =G15 * 7.2 -> 0 | I15: =IF(B15="Yes", 100, 40) -> 100 | J15: =IF(C15>30,I15*0.15,IF(D15>5,IF(B15="YES",24,12),I15)) -> 100 | K15: =I15-J15 -> 0 | L15: =K15 * 4 -> 0 | M15: Ideal BBQ Day | N15: 2023 | O15: May
A16: 45061 | B16: =IF( WEEKDAY(A16, 2) > 5, "YES", "NO") -> NO | C16: =_xlfn.XLOOKUP(A16,Weather_clean_data!A:A,Weather_clean_data!B:B,0) -> 16 | D16: =_xlfn.XLOOKUP(A16, Weather_clean_data!A:A, Weather_clean_data!C:C, 0) -> 0 | E16: =IF(B16="Yes", 150, 60) -> 60 | F16: =IF(C16>30,E16*0.15,IF(D16>5,IF(B16="YES",36,18),E16)) -> 60 | G16: =E16-F16 -> 0 | H16: =G16 * 7.2 -> 0 | I16: =IF(B16="Yes", 100, 40) -> 40 | J16: =IF(C16>30,I16*0.15,IF(D16>5,IF(B16="YES",24,12),I16)) -> 40 | K16: =I16-J16 -> 0 | L16: =K16 * 4 -> 0 | M16: Normal Weekday | N16: 2023 | O16: May
A17: 45062 | B17: =IF( WEEKDAY(A17, 2) > 5, "YES", "NO") -> NO | C17: =_xlfn.XLOOKUP(A17,Weather_clean_data!A:A,Weather_clean_data!B:B,0) -> 17 | D17: =_xlfn.XLOOKUP(A17, Weather_clean_data!A:A, Weather_clean_data!C:C, 0) -> 0 | E17: =IF(B17="Yes", 150, 60) -> 60 | F17: =IF(C17>30,E17*0.15,IF(D17>5,IF(B17="YES",36,18),E17)) -> 60 | G17: =E17-F17 -> 0 | H17: =G17 * 7.2 -> 0 | I17: =IF(B17="Yes", 100, 40) -> 40 | J17: =IF(C17>30,I17*0.15,IF(D17>5,IF(B17="YES",24,12),I17)) -> 40 | K17: =I17-J17 -> 0 | L17: =K17 * 4 -> 0 | M17: Normal Weekday | N17: 2023 | O17: May
A18: 45063 | B18: =IF( WEEKDAY(A18, 2) > 5, "YES", "NO") -> NO | C18: =_xlfn.XLOOKUP(A18,Weather_clean_data!A:A,Weather_clean_data!B:B,0) -> 18 | D18: =_xlfn.XLOOKUP(A18, Weather_clean_data!A:A, Weather_clean_data!C:C, 0) -> 0 | E18: =IF(B18="Yes", 150, 60) -> 60 | F18: =IF(C18>30,E18*0.15,IF(D18>5,IF(B18="YES",36,18),E18)) -> 60 | G18: =E18-F18 -> 0 | H18: =G18 * 7.2 -> 0 | I18: =IF(B18="Yes", 100, 40) -> 40 | J18: =IF(C18>30,I18*0.15,IF(D18>5,IF(B18="YES",24,12),I18)) -> 40 | K18: =I18-J18 -> 0 | L18: =K18 * 4 -> 0 | M18: Normal Weekday | N18: 2023 | O18: May
A19: 45064 | B19: =IF( WEEKDAY(A19, 2) > 5, "YES", "NO") -> NO | C19: =_xlfn.XLOOKUP(A19,Weather_clean_data!A:A,Weather_clean_data!B:B,0) -> 21 | D19: =_xlfn.XLOOKUP(A19, Weather_clean_data!A:A, Weather_clean_data!C:C, 0) -> 0 | E19: =IF(B19="Yes", 150, 60) -> 60 | F19: =IF(C19>30,E19*0.15,IF(D19>5,IF(B19="YES",36,18),E19)) -> 60 | G19: =E19-F19 -> 0 | H19: =G19 * 7.2 -> 0 | I19: =IF(B19="Yes", 100, 40) -> 40 | J19: =IF(C19>30,I19*0.15,IF(D19>5,IF(B19="YES",24,12),I19)) -> 40 | K19: =I19-J19 -> 0 | L19: =K19 * 4 -> 0 | M19: Normal Weekday | N19: 2023 | O19: May
A20: 45065 | B20: =IF( WEEKDAY(A20, 2) > 5, "YES", "NO") -> NO | C20: =_xlfn.XLOOKUP(A20,Weather_clean_data!A:A,Weather_clean_data!B:B,0) -> 19 | D20: =_xlfn.XLOOKUP(A20, Weather_clean_data!A:A, Weather_clean_data!C:C, 0) -> 2.3 | E20: =IF(B20="Yes", 150, 60) -> 60 | F20: =IF(C20>30,E20*0.15,IF(D20>5,IF(B20="YES",36,18),E20)) -> 60 | G20: =E20-F20 -> 0 | H20: =G20 * 7.2 -> 0 | I20: =IF(B20="Yes", 100, 40) -> 40 | J20: =IF(C20>30,I20*0.15,IF(D20>5,IF(B20="YES",24,12),I20)) -> 40 | K20: =I20-J20 -> 0 | L20: =K20 * 4 -> 0 | M20: Ideal BBQ Day | N20: 2023 | O20: May
A21: 45066 | B21: =IF( WEEKDAY(A21, 2) > 5, "YES", "NO") -> YES | C21: =_xlfn.XLOOKUP(A21,Weather_clean_data!A:A,Weather_clean_data!B:B,0) -> 19 | D21: =_xlfn.XLOOKUP(A21, Weather_clean_data!A:A, Weather_clean_data!C:C, 0) -> 0 | E21: =IF(B21="Yes", 150, 60) -> 150 | F21: =IF(C21>30,E21*0.15,IF(D21>5,IF(B21="YES",36,18),E21)) -> 150 | G21: =E21-F21 -> 0 | H21: =G21 * 7.2 -> 0 | I21: =IF(B21="Yes", 100, 40) -> 100 | J21: =IF(C21>30,I21*0.15,IF(D21>5,IF(B21="YES",24,12),I21)) -> 100 | K21: =I21-J21 -> 0 | L21: =K21 * 4 -> 0 | M21: Ideal BBQ Day | N21: 2023 | O21: May
... A29: 45074 | B29: =IF( WEEKDAY(A29, 2) > 5, "YES", "NO") -> YES | C29: =_xlfn.XLOOKUP(A29,Weather_clean_data!A:A,Weather_clean_data!B:B,0) -> 22 | D29: =_xlfn.XLOOKUP(A29, Weather_clean_data!A:A, Weather_clean_data!C:C, 0) -> 0 | E29: =IF(B29="Yes", 150, 60) -> 150 | F29: =IF(C29>30,E29*0.15,IF(D29>5,IF(B29="YES",36,18),E29)) -> 150 | G29: =E29-F29 -> 0 | H29: =G29 * 7.2 -> 0 | I29: =IF(B29="Yes", 100, 40) -> 100 | J29: =IF(C29>30,I29*0.15,IF(D29>5,IF(B29="YES",24,12),I29)) -> 100 | K29: =I29-J29 -> 0 | L29: =K29 * 4 -> 0 | M29: Ideal BBQ Day | N29: 2023 | O29: May
A30: 45075 | B30: YES | C30: =_xlfn.XLOOKUP(A30,Weather_clean_data!A:A,Weather_clean_data!B:B,0) -> 18 | D30: =_xlfn.XLOOKUP(A30, Weather_clean_data!A:A, Weather_clean_data!C:C, 0) -> 0 | E30: =IF(B30="Yes", 150, 60) -> 150 | F30: =IF(C30>30,E30*0.15,IF(D30>5,IF(B30="YES",36,18),E30)) -> 150 | G30: =E30-F30 -> 0 | H30: =G30 * 7.2 -> 0 | I30: =IF(B30="Yes", 100, 40) -> 100 | J30: =IF(C30>30,I30*0.15,IF(D30>5,IF(B30="YES",24,12),I30)) -> 100 | K30: =I30-J30 -> 0 | L30: =K30 * 4 -> 0 | M30: Ideal BBQ Day | N30: 2023 | O30: May
A31: 45076 | B31: =IF( WEEKDAY(A31, 2) > 5, "YES", "NO") -> NO | C31: =_xlfn.XLOOKUP(A31,Weather_clean_data!A:A,Weather_clean_data!B:B,0) -> 18 | D31: =_xlfn.XLOOKUP(A31, Weather_clean_data!A:A, Weather_clean_data!C:C, 0) -> 0 | E31: =IF(B31="Yes", 150, 60) -> 60 | F31: =IF(C31>30,E31*0.15,IF(D31>5,IF(B31="YES",36,18),E31)) -> 60 | G31: =E31-F31 -> 0 | H31: =G31 * 7.2 -> 0 | I31: =IF(B31="Yes", 100, 40) -> 40 | J31: =IF(C31>30,I31*0.15,IF(D31>5,IF(B31="YES",24,12),I31)) -> 40 | K31: =I31-J31 -> 0 | L31: =K31 * 4 -> 0 | M31: Normal Weekday | N31: 2023 | O31: May
A32: 45077 | B32: =IF( WEEKDAY(A32, 2) > 5, "YES", "NO") -> NO | C32: =_xlfn.XLOOKUP(A32,Weather_clean_data!A:A,Weather_clean_data!B:B,0) -> 15.2 | D32: =_xlfn.XLOOKUP(A32, Weather_clean_data!A:A, Weather_clean_data!C:C, 0) -> 0 | E32: =IF(B32="Yes", 150, 60) -> 60 | F32: =IF(C32>30,E32*0.15,IF(D32>5,IF(B32="YES",36,18),E32)) -> 60 | G32: =E32-F32 -> 0 | H32: =G32 * 7.2 -> 0 | I32: =IF(B32="Yes", 100, 40) -> 40 | J32: =IF(C32>30,I32*0.15,IF(D32>5,IF(B32="YES",24,12),I32)) -> 40 | K32: =I32-J32 -> 0 | L32: =K32 * 4 -> 0 | M32: Normal Weekday | N32: 2023 | O32: May
A33: 45078 | B33: =IF( WEEKDAY(A33, 2) > 5, "YES", "NO") -> NO | C33: =_xlfn.XLOOKUP(A33,Weather_clean_data!A:A,Weather_clean_data!B:B,0) -> 18 | D33: =_xlfn.XLOOKUP(A33, Weather_clean_data!A:A, Weather_clean_data!C:C, 0) -> 0 | E33: =IF(B33="Yes", 150, 60) -> 60 | F33: =IF(C33>30,E33*0.15,IF(D33>5,IF(B33="YES",36,18),E33)) -> 60 | G33: =E33-F33 -> 0 | H33: =G33 * 7.2 -> 0 | I33: =IF(B33="Yes", 100, 40) -> 40 | J33: =IF(C33>30,I33*0.15,IF(D33>5,IF(B33="YES",24,12),I33)) -> 40 | K33: =I33-J33 -> 0 | L33: =K33 * 4 -> 0 | M33: Normal Weekday | N33: 2023 | O33: June
A34: 45079 | B34: =IF( WEEKDAY(A34, 2) > 5, "YES", "NO") -> NO | C34: =_xlfn.XLOOKUP(A34,Weather_clean_data!A:A,Weather_clean_data!B:B,0) -> 19 | D34: =_xlfn.XLOOKUP(A34, Weather_clean_data!A:A, Weather_clean_data!C:C, 0) -> 0 | E34: =IF(B34="Yes", 150, 60) -> 60 | F34: =IF(C34>30,E34*0.15,IF(D34>5,IF(B34="YES",36,18),E34)) -> 60 | G34: =E34-F34 -> 0 | H34: =G34 * 7.2 -> 0 | I34: =IF(B34="Yes", 100, 40) -> 40 | J34: =IF(C34>30,I34*0.15,IF(D34>5,IF(B34="YES",24,12),I34)) -> 40 | K34: =I34-J34 -> 0 | L34: =K34 * 4 -> 0 | M34: Ideal BBQ Day | N34: 2023 | O34: June
A35: 45080 | B35: =IF( WEEKDAY(A35, 2) > 5, "YES", "NO") -> YES | C35: =_xlfn.XLOOKUP(A35,Weather_clean_data!A:A,Weather_clean_data!B:B,0) -> 22 | D35: =_xlfn.XLOOKUP(A35, Weather_clean_data!A:A, Weather_clean_data!C:C, 0) -> 0 | E35: =IF(B35="Yes", 150, 60) -> 150 | F35: =IF(C35>30,E35*0.15,IF(D35>5,IF(B35="YES",36,18),E35)) -> 150 | G35: =E35-F35 -> 0 | H35: =G35 * 7.2 -> 0 | I35: =IF(B35="Yes", 100, 40) -> 100 | J35: =IF(C35>30,I35*0.15,IF(D35>5,IF(B35="YES",24,12),I35)) -> 100 | K35: =I35-J35 -> 0 | L35: =K35 * 4 -> 0 | M35: Ideal BBQ Day | N35: 2023 | O35: June
A36: 45081 | B36: =IF( WEEKDAY(A36, 2) > 5, "YES", "NO") -> YES | C36: =_xlfn.XLOOKUP(A36,Weather_clean_data!A:A,Weather_clean_data!B:B,0) -> 21 | D36: =_xlfn.XLOOKUP(A36, Weather_clean_data!A:A, Weather_clean_data!C:C, 0) -> 0 | E36: =IF(B36="Yes", 150, 60) -> 150 | F36: =IF(C36>30,E36*0.15,IF(D36>5,IF(B36="YES",36,18),E36)) -> 150 | G36: =E36-F36 -> 0 | H36: =G36 * 7.2 -> 0 | I36: =IF(B36="Yes", 100, 40) -> 100 | J36: =IF(C36>30,I36*0.15,IF(D36>5,IF(B36="YES",24,12),I36)) -> 100 | K36: =I36-J36 -> 0 | L36: =K36 * 4 -> 0 | M36: Ideal BBQ Day | N36: 2023 | O36: June
A37: 45082 | B37: =IF( WEEKDAY(A37, 2) > 5, "YES", "NO") -> NO | C37: =_xlfn.XLOOKUP(A37,Weather_clean_data!A:A,Weather_clean_data!B:B,0) -> 18 | D37: =_xlfn.XLOOKUP(A37, Weather_clean_data!A:A, Weather_clean_data!C:C, 0) -> 0 | E37: =IF(B37="Yes", 150, 60) -> 60 | F37: =IF(C37>30,E37*0.15,IF(D37>5,IF(B37="YES",36,18),E37)) -> 60 | G37: =E37-F37 -> 0 | H37: =G37 * 7.2 -> 0 | I37: =IF(B37="Yes", 100, 40) -> 40 | J37: =IF(C37>30,I37*0.15,IF(D37>5,IF(B37="YES",24,12),I37)) -> 40 | K37: =I37-J37 -> 0 | L37: =K37 * 4 -> 0 | M37: Normal Weekday | N37: 2023 | O37: June
A38: 45083 | B38: =IF( WEEKDAY(A38, 2) > 5, "YES", "NO") -> NO | C38: =_xlfn.XLOOKUP(A38,Weather_clean_data!A:A,Weather_clean_data!B:B,0) -> 16 | D38: =_xlfn.XLOOKUP(A38, Weather_clean_data!A:A, Weather_clean_data!C:C, 0) -> 0 | E38: =IF(B38="Yes", 150, 60) -> 60 | F38: =IF(C38>30,E38*0.15,IF(D38>5,IF(B38="YES",36,18),E38)) -> 60 | G38: =E38-F38 -> 0 | H38: =G38 * 7.2 -> 0 | I38: =IF(B38="Yes", 100, 40) -> 40 | J38: =IF(C38>30,I38*0.15,IF(D38>5,IF(B38="YES",24,12),I38)) -> 40 | K38: =I38-J38 -> 0 | L38: =K38 * 4 -> 0 | M38: Normal Weekday | N38: 2023 | O38: June
A39: 45084 | B39: =IF( WEEKDAY(A39, 2) > 5, "YES", "NO") -> NO | C39: =_xlfn.XLOOKUP(A39,Weather_clean_data!A:A,Weather_clean_data!B:B,0) -> 21 | D39: =_xlfn.XLOOKUP(A39, Weather_clean_data!A:A, Weather_clean_data!C:C, 0) -> 0 | E39: =IF(B39="Yes", 150, 60) -> 60 | F39: =IF(C39>30,E39*0.15,IF(D39>5,IF(B39="YES",36,18),E39)) -> 60 | G39: =E39-F39 -> 0 | H39: =G39 * 7.2 -> 0 | I39: =IF(B39="Yes", 100, 40) -> 40 | J39: =IF(C39>30,I39*0.15,IF(D39>5,IF(B39="YES",24,12),I39)) -> 40 | K39: =I39-J39 -> 0 | L39: =K39 * 4 -> 0 | M39: Normal Weekday | N39: 2023 | O39: June
A40: 45085 | B40: =IF( WEEKDAY(A40, 2) > 5, "YES", "NO") -> NO | C40: =_xlfn.XLOOKUP(A40,Weather_clean_data!A:A,Weather_clean_data!B:B,0) -> 22 | D40: =_xlfn.XLOOKUP(A40, Weather_clean_data!A:A, Weather_clean_data!C:C, 0) -> 0 | E40: =IF(B40="Yes", 150, 60) -> 60 | F40: =IF(C40>30,E40*0.15,IF(D40>5,IF(B40="YES",36,18),E40)) -> 60 | G40: =E40-F40 -> 0 | H40: =G40 * 7.2 -> 0 | I40: =IF(B40="Yes", 100, 40) -> 40 | J40: =IF(C40>30,I40*0.15,IF(D40>5,IF(B40="YES",24,12),I40)) -> 40 | K40: =I40-J40 -> 0 | L40: =K40 * 4 -> 0 | M40: Normal Weekday | N40: 2023 | O40: June
A41: 45086 | B41: =IF( WEEKDAY(A41, 2) > 5, "YES", "NO") -> NO | C41: =_xlfn.XLOOKUP(A41,Weather_clean_data!A:A,Weather_clean_data!B:B,0) -> 25 | D41: =_xlfn.XLOOKUP(A41, Weather_clean_data!A:A, Weather_clean_data!C:C, 0) -> 0 | E41: =IF(B41="Yes", 150, 60) -> 60 | F41: =IF(C41>30,E41*0.15,IF(D41>5,IF(B41="YES",36,18),E41)) -> 60 | G41: =E41-F41 -> 0 | H41: =G41 * 7.2 -> 0 | I41: =IF(B41="Yes", 100, 40) -> 40 | J41: =IF(C41>30,I41*0.15,IF(D41>5,IF(B41="YES",24,12),I41)) -> 40 | K41: =I41-J41 -> 0 | L41: =K41 * 4 -> 0 | M41: Ideal BBQ Day | N41: 2023 | O41: June
A42: 45087 | B42: =IF( WEEKDAY(A42, 2) > 5, "YES", "NO") -> YES | C42: =_xlfn.XLOOKUP(A42,Weather_clean_data!A:A,Weather_clean_data!B:B,0) -> 29 | D42: =_xlfn.XLOOKUP(A42, Weather_clean_data!A:A, Weather_clean_data!C:C, 0) -> 0.8 | E42: =IF(B42="Yes", 150, 60) -> 150 | F42: =IF(C42>30,E42*0.15,IF(D42>5,IF(B42="YES",36,18),E42)) -> 150 | G42: =E42-F42 -> 0 | H42: =G42 * 7.2 -> 0 | I42: =IF(B42="Yes", 100, 40) -> 100 | J42: =IF(C42>30,I42*0.15,IF(D42>5,IF(B42="YES",24,12),I42)) -> 100 | K42: =I42-J42 -> 0 | L42: =K42 * 4 -> 0 | M42: Ideal BBQ Day | N42: 2023 | O42: June
... A127: 45781 | B127: =IF( WEEKDAY(A127, 2) > 5, "YES", "NO") -> YES | C127: =_xlfn.XLOOKUP(A127,Weather_clean_data!A:A,Weather_clean_data!B:B,0) -> 14 | D127: =_xlfn.XLOOKUP(A127, Weather_clean_data!A:A, Weather_clean_data!C:C, 0) -> 0 | E127: =IF(B127="Yes", 150, 60) -> 150 | F127: =IF(C127>30,E127*0.15,IF(D127>5,IF(B127="YES",36,18),E127)) -> 150 | G127: =E127-F127 -> 0 | H127: =G127 * 7.2 -> 0 | I127: =IF(B127="Yes", 100, 40) -> 100 | J127: =IF(C127>30,I127*0.15,IF(D127>5,IF(B127="YES",24,12),I127)) -> 100 | K127: =I127-J127 -> 0 | L127: =K127 * 4 -> 0 | M127: Ideal BBQ Day | N127: 2025 | O127: May
A128: 45782 | B128: YES | C128: =_xlfn.XLOOKUP(A128,Weather_clean_data!A:A,Weather_clean_data!B:B,0) -> 14 | D128: =_xlfn.XLOOKUP(A128, Weather_clean_data!A:A, Weather_clean_data!C:C, 0) -> 0 | E128: =IF(B128="Yes", 150, 60) -> 150 | F128: =IF(C128>30,E128*0.15,IF(D128>5,IF(B128="YES",36,18),E128)) -> 150 | G128: =E128-F128 -> 0 | H128: =G128 * 7.2 -> 0 | I128: =IF(B128="Yes", 100, 40) -> 100 | J128: =IF(C128>30,I128*0.15,IF(D128>5,IF(B128="YES",24,12),I128)) -> 100 | K128: =I128-J128 -> 0 | L128: =K128 * 4 -> 0 | M128: Ideal BBQ Day | N128: 2025 | O128: May
A129: 45783 | B129: =IF( WEEKDAY(A129, 2) > 5, "YES", "NO") -> NO | C129: =_xlfn.XLOOKUP(A129,Weather_clean_data!A:A,Weather_clean_data!B:B,0) -> 15 | D129: =_xlfn.XLOOKUP(A129, Weather_clean_data!A:A, Weather_clean_data!C:C, 0) -> 0 | E129: =IF(B129="Yes", 150, 60) -> 60 | F129: =IF(C129>30,E129*0.15,IF(D129>5,IF(B129="YES",36,18),E129)) -> 60 | G129: =E129-F129 -> 0 | H129: =G129 * 7.2 -> 0 | I129: =IF(B129="Yes", 100, 40) -> 40 | J129: =IF(C129>30,I129*0.15,IF(D129>5,IF(B129="YES",24,12),I129)) -> 40 | K129: =I129-J129 -> 0 | L129: =K129 * 4 -> 0 | M129: Normal Weekday | N129: 2025 | O129: May
A130: 45784 | B130: =IF( WEEKDAY(A130, 2) > 5, "YES", "NO") -> NO | C130: =_xlfn.XLOOKUP(A130,Weather_clean_data!A:A,Weather_clean_data!B:B,0) -> 18 | D130: =_xlfn.XLOOKUP(A130, Weather_clean_data!A:A, Weather_clean_data!C:C, 0) -> 0 | E130: =IF(B130="Yes", 150, 60) -> 60 | F130: =IF(C130>30,E130*0.15,IF(D130>5,IF(B130="YES",36,18),E130)) -> 60 | G130: =E130-F130 -> 0 | H130: =G130 * 7.2 -> 0 | I130: =IF(B130="Yes", 100, 40) -> 40 | J130: =IF(C130>30,I130*0.15,IF(D130>5,IF(B130="YES",24,12),I130)) -> 40 | K130: =I130-J130 -> 0 | L130: =K130 * 4 -> 0 | M130: Normal Weekday | N130: 2025 | O130: May
A131: 45785 | B131: =IF( WEEKDAY(A131, 2) > 5, "YES", "NO") -> NO | C131: =_xlfn.XLOOKUP(A131,Weather_clean_data!A:A,Weather_clean_data!B:B,0) -> 14 | D131: =_xlfn.XLOOKUP(A131, Weather_clean_data!A:A, Weather_clean_data!C:C, 0) -> 0 | E131: =IF(B131="Yes", 150, 60) -> 60 | F131: =IF(C131>30,E131*0.15,IF(D131>5,IF(B131="YES",36,18),E131)) -> 60 | G131: =E131-F131 -> 0 | H131: =G131 * 7.2 -> 0 | I131: =IF(B131="Yes", 100, 40) -> 40 | J131: =IF(C131>30,I131*0.15,IF(D131>5,IF(B131="YES",24,12),I131)) -> 40 | K131: =I131-J131 -> 0 | L131: =K131 * 4 -> 0 | M131: Normal Weekday | N131: 2025 | O131: May
A132: 45786 | B132: =IF( WEEKDAY(A132, 2) > 5, "YES", "NO") -> NO | C132: =_xlfn.XLOOKUP(A132,Weather_clean_data!A:A,Weather_clean_data!B:B,0) -> 20 | D132: =_xlfn.XLOOKUP(A132, Weather_clean_data!A:A, Weather_clean_data!C:C, 0) -> 0 | E132: =IF(B132="Yes", 150, 60) -> 60 | F132: =IF(C132>30,E132*0.15,IF(D132>5,IF(B132="YES",36,18),E132)) -> 60 | G132: =E132-F132 -> 0 | H132: =G132 * 7.2 -> 0 | I132: =IF(B132="Yes", 100, 40) -> 40 | J132: =IF(C132>30,I132*0.15,IF(D132>5,IF(B132="YES",24,12),I132)) -> 40 | K132: =I132-J132 -> 0 | L132: =K132 * 4 -> 0 | M132: Ideal BBQ Day | N132: 2025 | O132: May
A133: 45787 | B133: =IF( WEEKDAY(A133, 2) > 5, "YES", "NO") -> YES | C133: =_xlfn.XLOOKUP(A133,Weather_clean_data!A:A,Weather_clean_data!B:B,0) -> 23 | D133: =_xlfn.XLOOKUP(A133, Weather_clean_data!A:A, Weather_clean_data!C:C, 0) -> 0 | E133: =IF(B133="Yes", 150, 60) -> 150 | F133: =IF(C133>30,E133*0.15,IF(D133>5,IF(B133="YES",36,18),E133)) -> 150 | G133: =E133-F133 -> 0 | H133: =G133 * 7.2 -> 0 | I133: =IF(B133="Yes", 100, 40) -> 100 | J133: =IF(C133>30,I133*0.15,IF(D133>5,IF(B133="YES",24,12),I133)) -> 100 | K133: =I133-J133 -> 0 | L133: =K133 * 4 -> 0 | M133: Ideal BBQ Day | N133: 2025 | O133: May
A134: 45788 | B134: =IF( WEEKDAY(A134, 2) > 5, "YES", "NO") -> YES | C134: =_xlfn.XLOOKUP(A134,Weather_clean_data!A:A,Weather_clean_data!B:B,0) -> 24 | D134: =_xlfn.XLOOKUP(A134, Weather_clean_data!A:A, Weather_clean_data!C:C, 0) -> 1.5 | E134: =IF(B134="Yes", 150, 60) -> 150 | F134: =IF(C134>30,E134*0.15,IF(D134>5,IF(B134="YES",36,18),E134)) -> 150 | G134: =E134-F134 -> 0 | H134: =G134 * 7.2 -> 0 | I134: =IF(B134="Yes", 100, 40) -> 100 | J134: =IF(C134>30,I134*0.15,IF(D134>5,IF(B134="YES",24,12),I134)) -> 100 | K134: =I134-J134 -> 0 | L134: =K134 * 4 -> 0 | M134: Ideal BBQ Day | N134: 2025 | O134: May
A135: 45789 | B135: =IF( WEEKDAY(A135, 2) > 5, "YES", "NO") -> NO | C135: =_xlfn.XLOOKUP(A135,Weather_clean_data!A:A,Weather_clean_data!B:B,0) -> 23 | D135: =_xlfn.XLOOKUP(A135, Weather_clean_data!A:A, Weather_clean_data!C:C, 0) -> 0.7 | E135: =IF(B135="Yes", 150, 60) -> 60 | F135: =IF(C135>30,E135*0.15,IF(D135>5,IF(B135="YES",36,18),E135)) -> 60 | G135: =E135-F135 -> 0 | H135: =G135 * 7.2 -> 0 | I135: =IF(B135="Yes", 100, 40) -> 40 | J135: =IF(C135>30,I135*0.15,IF(D135>5,IF(B135="YES",24,12),I135)) -> 40 | K135: =I135-J135 -> 0 | L135: =K135 * 4 -> 0 | M135: Normal Weekday | N135: 2025 | O135: May
A136: 45790 | B136: =IF( WEEKDAY(A136, 2) > 5, "YES", "NO") -> NO | C136: =_xlfn.XLOOKUP(A136,Weather_clean_data!A:A,Weather_clean_data!B:B,0) -> 24 | D136: =_xlfn.XLOOKUP(A136, Weather_clean_data!A:A, Weather_clean_data!C:C, 0) -> 0.1 | E136: =IF(B136="Yes", 150, 60) -> 60 | F136: =IF(C136>30,E136*0.15,IF(D136>5,IF(B136="YES",36,18),E136)) -> 60 | G136: =E136-F136 -> 0 | H136: =G136 * 7.2 -> 0 | I136: =IF(B136="Yes", 100, 40) -> 40 | J136: =IF(C136>30,I136*0.15,IF(D136>5,IF(B136="YES",24,12),I136)) -> 40 | K136: =I136-J136 -> 0 | L136: =K136 * 4 -> 0 | M136: Normal Weekday | N136: 2025 | O136: May
A137: 45791 | B137: =IF( WEEKDAY(A137, 2) > 5, "YES", "NO") -> NO | C137: =_xlfn.XLOOKUP(A137,Weather_clean_data!A:A,Weather_clean_data!B:B,0) -> 22 | D137: =_xlfn.XLOOKUP(A137, Weather_clean_data!A:A, Weather_clean_data!C:C, 0) -> 0 | E137: =IF(B137="Yes", 150, 60) -> 60 | F137: =IF(C137>30,E137*0.15,IF(D137>5,IF(B137="YES",36,18),E137)) -> 60 | G137: =E137-F137 -> 0 | H137: =G137 * 7.2 -> 0 | I137: =IF(B137="Yes", 100, 40) -> 40 | J137: =IF(C137>30,I137*0.15,IF(D137>5,IF(B137="YES",24,12),I137)) -> 40 | K137: =I137-J137 -> 0 | L137: =K137 * 4 -> 0 | M137: Normal Weekday | N137: 2025 | O137: May
A138: 45792 | B138: =IF( WEEKDAY(A138, 2) > 5, "YES", "NO") -> NO | C138: =_xlfn.XLOOKUP(A138,Weather_clean_data!A:A,Weather_clean_data!B:B,0) -> 17 | D138: =_xlfn.XLOOKUP(A138, Weather_clean_data!A:A, Weather_clean_data!C:C, 0) -> 0 | E138: =IF(B138="Yes", 150, 60) -> 60 | F138: =IF(C138>30,E138*0.15,IF(D138>5,IF(B138="YES",36,18),E138)) -> 60 | G138: =E138-F138 -> 0 | H138: =G138 * 7.2 -> 0 | I138: =IF(B138="Yes", 100, 40) -> 40 | J138: =IF(C138>30,I138*0.15,IF(D138>5,IF(B138="YES",24,12),I138)) -> 40 | K138: =I138-J138 -> 0 | L138: =K138 * 4 -> 0 | M138: Normal Weekday | N138: 2025 | O138: May
A139: 45793 | B139: =IF( WEEKDAY(A139, 2) > 5, "YES", "NO") -> NO | C139: =_xlfn.XLOOKUP(A139,Weather_clean_data!A:A,Weather_clean_data!B:B,0) -> 22 | D139: =_xlfn.XLOOKUP(A139, Weather_clean_data!A:A, Weather_clean_data!C:C, 0) -> 0 | E139: =IF(B139="Yes", 150, 60) -> 60 | F139: =IF(C139>30,E139*0.15,IF(D139>5,IF(B139="YES",36,18),E139)) -> 60 | G139: =E139-F139 -> 0 | H139: =G139 * 7.2 -> 0 | I139: =IF(B139="Yes", 100, 40) -> 40 | J139: =IF(C139>30,I139*0.15,IF(D139>5,IF(B139="YES",24,12),I139)) -> 40 | K139: =I139-J139 -> 0 | L139: =K139 * 4 -> 0 | M139: Ideal BBQ Day | N139: 2025 | O139: May
A140: 45794 | B140: =IF( WEEKDAY(A140, 2) > 5, "YES", "NO") -> YES | C140: =_xlfn.XLOOKUP(A140,Weather_clean_data!A:A,Weather_clean_data!B:B,0) -> 17 | D140: =_xlfn.XLOOKUP(A140, Weather_clean_data!A:A, Weather_clean_data!C:C, 0) -> 0 | E140: =IF(B140="Yes", 150, 60) -> 150 | F140: =IF(C140>30,E140*0.15,IF(D140>5,IF(B140="YES",36,18),E140)) -> 150 | G140: =E140-F140 -> 0 | H140: =G140 * 7.2 -> 0 | I140: =IF(B140="Yes", 100, 40) -> 100 | J140: =IF(C140>30,I140*0.15,IF(D140>5,IF(B140="YES",24,12),I140)) -> 100 | K140: =I140-J140 -> 0 | L140: =K140 * 4 -> 0 | M140: Ideal BBQ Day | N140: 2025 | O140: May
... A148: 45802 | B148: =IF( WEEKDAY(A148, 2) > 5, "YES", "NO") -> YES | C148: =_xlfn.XLOOKUP(A148,Weather_clean_data!A:A,Weather_clean_data!B:B,0) -> 19 | D148: =_xlfn.XLOOKUP(A148, Weather_clean_data!A:A, Weather_clean_data!C:C, 0) -> 0.4 | E148: =IF(B148="Yes", 150, 60) -> 150 | F148: =IF(C148>30,E148*0.15,IF(D148>5,IF(B148="YES",36,18),E148)) -> 150 | G148: =E148-F148 -> 0 | H148: =G148 * 7.2 -> 0 | I148: =IF(B148="Yes", 100, 40) -> 100 | J148: =IF(C148>30,I148*0.15,IF(D148>5,IF(B148="YES",24,12),I148)) -> 100 | K148: =I148-J148 -> 0 | L148: =K148 * 4 -> 0 | M148: Ideal BBQ Day | N148: 2025 | O148: May
A149: 45803 | B149: YES | C149: =_xlfn.XLOOKUP(A149,Weather_clean_data!A:A,Weather_clean_data!B:B,0) -> 17 | D149: =_xlfn.XLOOKUP(A149, Weather_clean_data!A:A, Weather_clean_data!C:C, 0) -> 0.6 | E149: =IF(B149="Yes", 150, 60) -> 150 | F149: =IF(C149>30,E149*0.15,IF(D149>5,IF(B149="YES",36,18),E149)) -> 150 | G149: =E149-F149 -> 0 | H149: =G149 * 7.2 -> 0 | I149: =IF(B149="Yes", 100, 40) -> 100 | J149: =IF(C149>30,I149*0.15,IF(D149>5,IF(B149="YES",24,12),I149)) -> 100 | K149: =I149-J149 -> 0 | L149: =K149 * 4 -> 0 | M149: Ideal BBQ Day | N149: 2025 | O149: May
A150: 45804 | B150: =IF( WEEKDAY(A150, 2) > 5, "YES", "NO") -> NO | C150: =_xlfn.XLOOKUP(A150,Weather_clean_data!A:A,Weather_clean_data!B:B,0) -> 17 | D150: =_xlfn.XLOOKUP(A150, Weather_clean_data!A:A, Weather_clean_data!C:C, 0) -> 6.1 | E150: =IF(B150="Yes", 150, 60) -> 60 | F150: =IF(C150>30,E150*0.15,IF(D150>5,IF(B150="YES",36,18),E150)) -> 18 | G150: =E150-F150 -> 42 | H150: =G150 * 7.2 -> 302.4 | I150: =IF(B150="Yes", 100, 40) -> 40 | J150: =IF(C150>30,I150*0.15,IF(D150>5,IF(B150="YES",24,12),I150)) -> 12 | K150: =I150-J150 -> 28 | L150: =K150 * 4 -> 112 | M150: Heavy Rain | N150: 2025 | O150: May
A151: 45805 | B151: =IF( WEEKDAY(A151, 2) > 5, "YES", "NO") -> NO | C151: =_xlfn.XLOOKUP(A151,Weather_clean_data!A:A,Weather_clean_data!B:B,0) -> 20 | D151: =_xlfn.XLOOKUP(A151, Weather_clean_data!A:A, Weather_clean_data!C:C, 0) -> 1.9 | E151: =IF(B151="Yes", 150, 60) -> 60 | F151: =IF(C151>30,E151*0.15,IF(D151>5,IF(B151="YES",36,18),E151)) -> 60 | G151: =E151-F151 -> 0 | H151: =G151 * 7.2 -> 0 | I151: =IF(B151="Yes", 100, 40) -> 40 | J151: =IF(C151>30,I151*0.15,IF(D151>5,IF(B151="YES",24,12),I151)) -> 40 | K151: =I151-J151 -> 0 | L151: =K151 * 4 -> 0 | M151: Normal Weekday | N151: 2025 | O151: May
A152: 45806 | B152: =IF( WEEKDAY(A152, 2) > 5, "YES", "NO") -> NO | C152: =_xlfn.XLOOKUP(A152,Weather_clean_data!A:A,Weather_clean_data!B:B,0) -> 23 | D152: =_xlfn.XLOOKUP(A152, Weather_clean_data!A:A, Weather_clean_data!C:C, 0) -> 0.4 | E152: =IF(B152="Yes", 150, 60) -> 60 | F152: =IF(C152>30,E152*0.15,IF(D152>5,IF(B152="YES",36,18),E152)) -> 60 | G152: =E152-F152 -> 0 | H152: =G152 * 7.2 -> 0 | I152: =IF(B152="Yes", 100, 40) -> 40 | J152: =IF(C152>30,I152*0.15,IF(D152>5,IF(B152="YES",24,12),I152)) -> 40 | K152: =I152-J152 -> 0 | L152: =K152 * 4 -> 0 | M152: Normal Weekday | N152: 2025 | O152: May
A153: 45807 | B153: =IF( WEEKDAY(A153, 2) > 5, "YES", "NO") -> NO | C153: =_xlfn.XLOOKUP(A153,Weather_clean_data!A:A,Weather_clean_data!B:B,0) -> 23 | D153: =_xlfn.XLOOKUP(A153, Weather_clean_data!A:A, Weather_clean_data!C:C, 0) -> 0 | E153: =IF(B153="Yes", 150, 60) -> 60 | F153: =IF(C153>30,E153*0.15,IF(D153>5,IF(B153="YES",36,18),E153)) -> 60 | G153: =E153-F153 -> 0 | H153: =G153 * 7.2 -> 0 | I153: =IF(B153="Yes", 100, 40) -> 40 | J153: =IF(C153>30,I153*0.15,IF(D153>5,IF(B153="YES",24,12),I153)) -> 40 | K153: =I153-J153 -> 0 | L153: =K153 * 4 -> 0 | M153: Ideal BBQ Day | N153: 2025 | O153: May
A154: 45808 | B154: =IF( WEEKDAY(A154, 2) > 5, "YES", "NO") -> YES | C154: =_xlfn.XLOOKUP(A154,Weather_clean_data!A:A,Weather_clean_data!B:B,0) -> 23 | D154: =_xlfn.XLOOKUP(A154, Weather_clean_data!A:A, Weather_clean_data!C:C, 0) -> 0 | E154: =IF(B154="Yes", 150, 60) -> 150 | F154: =IF(C154>30,E154*0.15,IF(D154>5,IF(B154="YES",36,18),E154)) -> 150 | G154: =E154-F154 -> 0 | H154: =G154 * 7.2 -> 0 | I154: =IF(B154="Yes", 100, 40) -> 100 | J154: =IF(C154>30,I154*0.15,IF(D154>5,IF(B154="YES",24,12),I154)) -> 100 | K154: =I154-J154 -> 0 | L154: =K154 * 4 -> 0 | M154: Ideal BBQ Day | N154: 2025 | O154: May
A155: 45809 | B155: =IF( WEEKDAY(A155, 2) > 5, "YES", "NO") -> YES | C155: =_xlfn.XLOOKUP(A155,Weather_clean_data!A:A,Weather_clean_data!B:B,0) -> 19 | D155: =_xlfn.XLOOKUP(A155, Weather_clean_data!A:A, Weather_clean_data!C:C, 0) -> 0.2 | E155: =IF(B155="Yes", 150, 60) -> 150 | F155: =IF(C155>30,E155*0.15,IF(D155>5,IF(B155="YES",36,18),E155)) -> 150 | G155: =E155-F155 -> 0 | H155: =G155 * 7.2 -> 0 | I155: =IF(B155="Yes", 100, 40) -> 100 | J155: =IF(C155>30,I155*0.15,IF(D155>5,IF(B155="YES",24,12),I155)) -> 100 | K155: =I155-J155 -> 0 | L155: =K155 * 4 -> 0 | M155: Ideal BBQ Day | N155: 2025 | O155: June
A156: 45810 | B156: =IF( WEEKDAY(A156, 2) > 5, "YES", "NO") -> NO | C156: =_xlfn.XLOOKUP(A156,Weather_clean_data!A:A,Weather_clean_data!B:B,0) -> 20 | D156: =_xlfn.XLOOKUP(A156, Weather_clean_data!A:A, Weather_clean_data!C:C, 0) -> 0 | E156: =IF(B156="Yes", 150, 60) -> 60 | F156: =IF(C156>30,E156*0.15,IF(D156>5,IF(B156="YES",36,18),E156)) -> 60 | G156: =E156-F156 -> 0 | H156: =G156 * 7.2 -> 0 | I156: =IF(B156="Yes", 100, 40) -> 40 | J156: =IF(C156>30,I156*0.15,IF(D156>5,IF(B156="YES",24,12),I156)) -> 40 | K156: =I156-J156 -> 0 | L156: =K156 * 4 -> 0 | M156: Normal Weekday | N156: 2025 | O156: June
A157: 45811 | B157: =IF( WEEKDAY(A157, 2) > 5, "YES", "NO") -> NO | C157: =_xlfn.XLOOKUP(A157,Weather_clean_data!A:A,Weather_clean_data!B:B,0) -> 19 | D157: =_xlfn.XLOOKUP(A157, Weather_clean_data!A:A, Weather_clean_data!C:C, 0) -> 4.5 | E157: =IF(B157="Yes", 150, 60) -> 60 | F157: =IF(C157>30,E157*0.15,IF(D157>5,IF(B157="YES",36,18),E157)) -> 60 | G157: =E157-F157 -> 0 | H157: =G157 * 7.2 -> 0 | I157: =IF(B157="Yes", 100, 40) -> 40 | J157: =IF(C157>30,I157*0.15,IF(D157>5,IF(B157="YES",24,12),I157)) -> 40 | K157: =I157-J157 -> 0 | L157: =K157 * 4 -> 0 | M157: Normal Weekday | N157: 2025 | O157: June
A158: 45812 | B158: =IF( WEEKDAY(A158, 2) > 5, "YES", "NO") -> NO | C158: =_xlfn.XLOOKUP(A158,Weather_clean_data!A:A,Weather_clean_data!B:B,0) -> 19 | D158: =_xlfn.XLOOKUP(A158, Weather_clean_data!A:A, Weather_clean_data!C:C, 0) -> 0 | E158: =IF(B158="Yes", 150, 60) -> 60 | F158: =IF(C158>30,E158*0.15,IF(D158>5,IF(B158="YES",36,18),E158)) -> 60 | G158: =E158-F158 -> 0 | H158: =G158 * 7.2 -> 0 | I158: =IF(B158="Yes", 100, 40) -> 40 | J158: =IF(C158>30,I158*0.15,IF(D158>5,IF(B158="YES",24,12),I158)) -> 40 | K158: =I158-J158 -> 0 | L158: =K158 * 4 -> 0 | M158: Normal Weekday | N158: 2025 | O158: June
A159: 45813 | B159: =IF( WEEKDAY(A159, 2) > 5, "YES", "NO") -> NO | C159: =_xlfn.XLOOKUP(A159,Weather_clean_data!A:A,Weather_clean_data!B:B,0) -> 17 | D159: =_xlfn.XLOOKUP(A159, Weather_clean_data!A:A, Weather_clean_data!C:C, 0) -> 3.5 | E159: =IF(B159="Yes", 150, 60) -> 60 | F159: =IF(C159>30,E159*0.15,IF(D159>5,IF(B159="YES",36,18),E159)) -> 60 | G159: =E159-F159 -> 0 | H159: =G159 * 7.2 -> 0 | I159: =IF(B159="Yes", 100, 40) -> 40 | J159: =IF(C159>30,I159*0.15,IF(D159>5,IF(B159="YES",24,12),I159)) -> 40 | K159: =I159-J159 -> 0 | L159: =K159 * 4 -> 0 | M159: Normal Weekday | N159: 2025 | O159: June
A160: 45814 | B160: =IF( WEEKDAY(A160, 2) > 5, "YES", "NO") -> NO | C160: =_xlfn.XLOOKUP(A160,Weather_clean_data!A:A,Weather_clean_data!B:B,0) -> 19 | D160: =_xlfn.XLOOKUP(A160, Weather_clean_data!A:A, Weather_clean_data!C:C, 0) -> 0.3 | E160: =IF(B160="Yes", 150, 60) -> 60 | F160: =IF(C160>30,E160*0.15,IF(D160>5,IF(B160="YES",36,18),E160)) -> 60 | G160: =E160-F160 -> 0 | H160: =G160 * 7.2 -> 0 | I160: =IF(B160="Yes", 100, 40) -> 40 | J160: =IF(C160>30,I160*0.15,IF(D160>5,IF(B160="YES",24,12),I160)) -> 40 | K160: =I160-J160 -> 0 | L160: =K160 * 4 -> 0 | M160: Ideal BBQ Day | N160: 2025 | O160: June
A161: 45815 | B161: =IF( WEEKDAY(A161, 2) > 5, "YES", "NO") -> YES | C161: =_xlfn.XLOOKUP(A161,Weather_clean_data!A:A,Weather_clean_data!B:B,0) -> 16 | D161: =_xlfn.XLOOKUP(A161, Weather_clean_data!A:A, Weather_clean_data!C:C, 0) -> 16.2 | E161: =IF(B161="Yes", 150, 60) -> 150 | F161: =IF(C161>30,E161*0.15,IF(D161>5,IF(B161="YES",36,18),E161)) -> 36 | G161: =E161-F161 -> 114 | H161: =G161 * 7.2 -> 820.8 | I161: =IF(B161="Yes", 100, 40) -> 100 | J161: =IF(C161>30,I161*0.15,IF(D161>5,IF(B161="YES",24,12),I161)) -> 24 | K161: =I161-J161 -> 76 | L161: =K161 * 4 -> 304 | M161: Heavy Rain | N161: 2025 | O161: June
... A187: 46145 | B187: =IF( WEEKDAY(A187, 2) > 5, "YES", "NO") -> YES | C187: =_xlfn.XLOOKUP(A187,Weather_clean_data!A:A,Weather_clean_data!B:B,0) -> 17.4 | D187: =_xlfn.XLOOKUP(A187, Weather_clean_data!A:A, Weather_clean_data!C:C, 0) -> 2.9 | E187: =IF(B187="Yes", 150, 60) -> 150 | F187: =IF(C187>30,E187*0.15,IF(D187>5,IF(B187="YES",36,18),E187)) -> 150 | G187: =E187-F187 -> 0 | H187: =G187 * 7.2 -> 0 | I187: =IF(B187="Yes", 100, 40) -> 100 | J187: =IF(C187>30,I187*0.15,IF(D187>5,IF(B187="YES",24,12),I187)) -> 100 | K187: =I187-J187 -> 0 | L187: =K187 * 4 -> 0 | M187: Ideal BBQ Day | N187: 2026 | O187: May
A188: 46146 | B188: YES | C188: =_xlfn.XLOOKUP(A188,Weather_clean_data!A:A,Weather_clean_data!B:B,0) -> 16 | D188: =_xlfn.XLOOKUP(A188, Weather_clean_data!A:A, Weather_clean_data!C:C, 0) -> 1.9 | E188: =IF(B188="Yes", 150, 60) -> 150 | F188: =IF(C188>30,E188*0.15,IF(D188>5,IF(B188="YES",36,18),E188)) -> 150 | G188: =E188-F188 -> 0 | H188: =G188 * 7.2 -> 0 | I188: =IF(B188="Yes", 100, 40) -> 100 | J188: =IF(C188>30,I188*0.15,IF(D188>5,IF(B188="YES",24,12),I188)) -> 100 | K188: =I188-J188 -> 0 | L188: =K188 * 4 -> 0 | M188: Ideal BBQ Day | N188: 2026 | O188: May
A189: 46147 | B189: =IF( WEEKDAY(A189, 2) > 5, "YES", "NO") -> NO | C189: =_xlfn.XLOOKUP(A189,Weather_clean_data!A:A,Weather_clean_data!B:B,0) -> 15 | D189: =_xlfn.XLOOKUP(A189, Weather_clean_data!A:A, Weather_clean_data!C:C, 0) -> 0 | E189: =IF(B189="Yes", 150, 60) -> 60 | F189: =IF(C189>30,E189*0.15,IF(D189>5,IF(B189="YES",36,18),E189)) -> 60 | G189: =E189-F189 -> 0 | H189: =G189 * 7.2 -> 0 | I189: =IF(B189="Yes", 100, 40) -> 40 | J189: =IF(C189>30,I189*0.15,IF(D189>5,IF(B189="YES",24,12),I189)) -> 40 | K189: =I189-J189 -> 0 | L189: =K189 * 4 -> 0 | M189: Normal Weekday | N189: 2026 | O189: May
A190: 46148 | B190: =IF( WEEKDAY(A190, 2) > 5, "YES", "NO") -> NO | C190: =_xlfn.XLOOKUP(A190,Weather_clean_data!A:A,Weather_clean_data!B:B,0) -> 14 | D190: =_xlfn.XLOOKUP(A190, Weather_clean_data!A:A, Weather_clean_data!C:C, 0) -> 0 | E190: =IF(B190="Yes", 150, 60) -> 60 | F190: =IF(C190>30,E190*0.15,IF(D190>5,IF(B190="YES",36,18),E190)) -> 60 | G190: =E190-F190 -> 0 | H190: =G190 * 7.2 -> 0 | I190: =IF(B190="Yes", 100, 40) -> 40 | J190: =IF(C190>30,I190*0.15,IF(D190>5,IF(B190="YES",24,12),I190)) -> 40 | K190: =I190-J190 -> 0 | L190: =K190 * 4 -> 0 | M190: Normal Weekday | N190: 2026 | O190: May
A191: 46149 | B191: =IF( WEEKDAY(A191, 2) > 5, "YES", "NO") -> NO | C191: =_xlfn.XLOOKUP(A191,Weather_clean_data!A:A,Weather_clean_data!B:B,0) -> 16 | D191: =_xlfn.XLOOKUP(A191, Weather_clean_data!A:A, Weather_clean_data!C:C, 0) -> 1 | E191: =IF(B191="Yes", 150, 60) -> 60 | F191: =IF(C191>30,E191*0.15,IF(D191>5,IF(B191="YES",36,18),E191)) -> 60 | G191: =E191-F191 -> 0 | H191: =G191 * 7.2 -> 0 | I191: =IF(B191="Yes", 100, 40) -> 40 | J191: =IF(C191>30,I191*0.15,IF(D191>5,IF(B191="YES",24,12),I191)) -> 40 | K191: =I191-J191 -> 0 | L191: =K191 * 4 -> 0 | M191: Normal Weekday | N191: 2026 | O191: May
A192: 46150 | B192: =IF( WEEKDAY(A192, 2) > 5, "YES", "NO") -> NO | C192: =_xlfn.XLOOKUP(A192,Weather_clean_data!A:A,Weather_clean_data!B:B,0) -> 18 | D192: =_xlfn.XLOOKUP(A192, Weather_clean_data!A:A, Weather_clean_data!C:C, 0) -> 3.8 | E192: =IF(B192="Yes", 150, 60) -> 60 | F192: =IF(C192>30,E192*0.15,IF(D192>5,IF(B192="YES",36,18),E192)) -> 60 | G192: =E192-F192 -> 0 | H192: =G192 * 7.2 -> 0 | I192: =IF(B192="Yes", 100, 40) -> 40 | J192: =IF(C192>30,I192*0.15,IF(D192>5,IF(B192="YES",24,12),I192)) -> 40 | K192: =I192-J192 -> 0 | L192: =K192 * 4 -> 0 | M192: Ideal BBQ Day | N192: 2026 | O192: May
A193: 46151 | B193: =IF( WEEKDAY(A193, 2) > 5, "YES", "NO") -> YES | C193: =_xlfn.XLOOKUP(A193,Weather_clean_data!A:A,Weather_clean_data!B:B,0) -> 20 | D193: =_xlfn.XLOOKUP(A193, Weather_clean_data!A:A, Weather_clean_data!C:C, 0) -> 0 | E193: =IF(B193="Yes", 150, 60) -> 150 | F193: =IF(C193>30,E193*0.15,IF(D193>5,IF(B193="YES",36,18),E193)) -> 150 | G193: =E193-F193 -> 0 | H193: =G193 * 7.2 -> 0 | I193: =IF(B193="Yes", 100, 40) -> 100 | J193: =IF(C193>30,I193*0.15,IF(D193>5,IF(B193="YES",24,12),I193)) -> 100 | K193: =I193-J193 -> 0 | L193: =K193 * 4 -> 0 | M193: Ideal BBQ Day | N193: 2026 | O193: May
A194: 46152 | B194: =IF( WEEKDAY(A194, 2) > 5, "YES", "NO") -> YES | C194: =_xlfn.XLOOKUP(A194,Weather_clean_data!A:A,Weather_clean_data!B:B,0) -> 14 | D194: =_xlfn.XLOOKUP(A194, Weather_clean_data!A:A, Weather_clean_data!C:C, 0) -> 0 | E194: =IF(B194="Yes", 150, 60) -> 150 | F194: =IF(C194>30,E194*0.15,IF(D194>5,IF(B194="YES",36,18),E194)) -> 150 | G194: =E194-F194 -> 0 | H194: =G194 * 7.2 -> 0 | I194: =IF(B194="Yes", 100, 40) -> 100 | J194: =IF(C194>30,I194*0.15,IF(D194>5,IF(B194="YES",24,12),I194)) -> 100 | K194: =I194-J194 -> 0 | L194: =K194 * 4 -> 0 | M194: Ideal BBQ Day | N194: 2026 | O194: May
A195: 46153 | B195: =IF( WEEKDAY(A195, 2) > 5, "YES", "NO") -> NO | C195: =_xlfn.XLOOKUP(A195,Weather_clean_data!A:A,Weather_clean_data!B:B,0) -> 13 | D195: =_xlfn.XLOOKUP(A195, Weather_clean_data!A:A, Weather_clean_data!C:C, 0) -> 0.5 | E195: =IF(B195="Yes", 150, 60) -> 60 | F195: =IF(C195>30,E195*0.15,IF(D195>5,IF(B195="YES",36,18),E195)) -> 60 | G195: =E195-F195 -> 0 | H195: =G195 * 7.2 -> 0 | I195: =IF(B195="Yes", 100, 40) -> 40 | J195: =IF(C195>30,I195*0.15,IF(D195>5,IF(B195="YES",24,12),I195)) -> 40 | K195: =I195-J195 -> 0 | L195: =K195 * 4 -> 0 | M195: Normal Weekday | N195: 2026 | O195: May
A196: 46154 | B196: =IF( WEEKDAY(A196, 2) > 5, "YES", "NO") -> NO | C196: =_xlfn.XLOOKUP(A196,Weather_clean_data!A:A,Weather_clean_data!B:B,0) -> 16 | D196: =_xlfn.XLOOKUP(A196, Weather_clean_data!A:A, Weather_clean_data!C:C, 0) -> 0.1 | E196: =IF(B196="Yes", 150, 60) -> 60 | F196: =IF(C196>30,E196*0.15,IF(D196>5,IF(B196="YES",36,18),E196)) -> 60 | G196: =E196-F196 -> 0 | H196: =G196 * 7.2 -> 0 | I196: =IF(B196="Yes", 100, 40) -> 40 | J196: =IF(C196>30,I196*0.15,IF(D196>5,IF(B196="YES",24,12),I196)) -> 40 | K196: =I196-J196 -> 0 | L196: =K196 * 4 -> 0 | M196: Normal Weekday | N196: 2026 | O196: May
A197: 46155 | B197: =IF( WEEKDAY(A197, 2) > 5, "YES", "NO") -> NO | C197: =_xlfn.XLOOKUP(A197,Weather_clean_data!A:A,Weather_clean_data!B:B,0) -> 13 | D197: =_xlfn.XLOOKUP(A197, Weather_clean_data!A:A, Weather_clean_data!C:C, 0) -> 1.4 | E197: =IF(B197="Yes", 150, 60) -> 60 | F197: =IF(C197>30,E197*0.15,IF(D197>5,IF(B197="YES",36,18),E197)) -> 60 | G197: =E197-F197 -> 0 | H197: =G197 * 7.2 -> 0 | I197: =IF(B197="Yes", 100, 40) -> 40 | J197: =IF(C197>30,I197*0.15,IF(D197>5,IF(B197="YES",24,12),I197)) -> 40 | K197: =I197-J197 -> 0 | L197: =K197 * 4 -> 0 | M197: Normal Weekday | N197: 2026 | O197: May
A198: 46156 | B198: =IF( WEEKDAY(A198, 2) > 5, "YES", "NO") -> NO | C198: =_xlfn.XLOOKUP(A198,Weather_clean_data!A:A,Weather_clean_data!B:B,0) -> 13 | D198: =_xlfn.XLOOKUP(A198, Weather_clean_data!A:A, Weather_clean_data!C:C, 0) -> 2.8 | E198: =IF(B198="Yes", 150, 60) -> 60 | F198: =IF(C198>30,E198*0.15,IF(D198>5,IF(B198="YES",36,18),E198)) -> 60 | G198: =E198-F198 -> 0 | H198: =G198 * 7.2 -> 0 | I198: =IF(B198="Yes", 100, 40) -> 40 | J198: =IF(C198>30,I198*0.15,IF(D198>5,IF(B198="YES",24,12),I198)) -> 40 | K198: =I198-J198 -> 0 | L198: =K198 * 4 -> 0 | M198: Normal Weekday | N198: 2026 | O198: May
A199: 46157 | B199: =IF( WEEKDAY(A199, 2) > 5, "YES", "NO") -> NO | C199: =_xlfn.XLOOKUP(A199,Weather_clean_data!A:A,Weather_clean_data!B:B,0) -> 13 | D199: =_xlfn.XLOOKUP(A199, Weather_clean_data!A:A, Weather_clean_data!C:C, 0) -> 0.1 | E199: =IF(B199="Yes", 150, 60) -> 60 | F199: =IF(C199>30,E199*0.15,IF(D199>5,IF(B199="YES",36,18),E199)) -> 60 | G199: =E199-F199 -> 0 | H199: =G199 * 7.2 -> 0 | I199: =IF(B199="Yes", 100, 40) -> 40 | J199: =IF(C199>30,I199*0.15,IF(D199>5,IF(B199="YES",24,12),I199)) -> 40 | K199: =I199-J199 -> 0 | L199: =K199 * 4 -> 0 | M199: Ideal BBQ Day | N199: 2026 | O199: May
A200: 46158 | B200: =IF( WEEKDAY(A200, 2) > 5, "YES", "NO") -> YES | C200: =_xlfn.XLOOKUP(A200,Weather_clean_data!A:A,Weather_clean_data!B:B,0) -> 14 | D200: =_xlfn.XLOOKUP(A200, Weather_clean_data!A:A, Weather_clean_data!C:C, 0) -> 2.2 | E200: =IF(B200="Yes", 150, 60) -> 150 | F200: =IF(C200>30,E200*0.15,IF(D200>5,IF(B200="YES",36,18),E200)) -> 150 | G200: =E200-F200 -> 0 | H200: =G200 * 7.2 -> 0 | I200: =IF(B200="Yes", 100, 40) -> 100 | J200: =IF(C200>30,I200*0.15,IF(D200>5,IF(B200="YES",24,12),I200)) -> 100 | K200: =I200-J200 -> 0 | L200: =K200 * 4 -> 0 | M200: Ideal BBQ Day | N200: 2026 | O200: May
... A208: 46166 | B208: =IF( WEEKDAY(A208, 2) > 5, "YES", "NO") -> YES | C208: =_xlfn.XLOOKUP(A208,Weather_clean_data!A:A,Weather_clean_data!B:B,0) -> 28 | D208: =_xlfn.XLOOKUP(A208, Weather_clean_data!A:A, Weather_clean_data!C:C, 0) -> 0 | E208: =IF(B208="Yes", 150, 60) -> 150 | F208: =IF(C208>30,E208*0.15,IF(D208>5,IF(B208="YES",36,18),E208)) -> 150 | G208: =E208-F208 -> 0 | H208: =G208 * 7.2 -> 0 | I208: =IF(B208="Yes", 100, 40) -> 100 | J208: =IF(C208>30,I208*0.15,IF(D208>5,IF(B208="YES",24,12),I208)) -> 100 | K208: =I208-J208 -> 0 | L208: =K208 * 4 -> 0 | M208: Ideal BBQ Day | N208: 2026 | O208: May
A209: 46167 | B209: YES | C209: =_xlfn.XLOOKUP(A209,Weather_clean_data!A:A,Weather_clean_data!B:B,0) -> 33 | D209: =_xlfn.XLOOKUP(A209, Weather_clean_data!A:A, Weather_clean_data!C:C, 0) -> 0 | E209: =IF(B209="Yes", 150, 60) -> 150 | F209: =IF(C209>30,E209*0.15,IF(D209>5,IF(B209="YES",36,18),E209)) -> 22.5 | G209: =E209-F209 -> 127.5 | H209: =G209 * 7.2 -> 918 | I209: =IF(B209="Yes", 100, 40) -> 100 | J209: =IF(C209>30,I209*0.15,IF(D209>5,IF(B209="YES",24,12),I209)) -> 15 | K209: =I209-J209 -> 85 | L209: =K209 * 4 -> 340 | M209: Extreme Heat | N209: 2026 | O209: May
A210: 46168 | B210: =IF( WEEKDAY(A210, 2) > 5, "YES", "NO") -> NO | C210: =_xlfn.XLOOKUP(A210,Weather_clean_data!A:A,Weather_clean_data!B:B,0) -> 32 | D210: =_xlfn.XLOOKUP(A210, Weather_clean_data!A:A, Weather_clean_data!C:C, 0) -> 0 | E210: =IF(B210="Yes", 150, 60) -> 60 | F210: =IF(C210>30,E210*0.15,IF(D210>5,IF(B210="YES",36,18),E210)) -> 9 | G210: =E210-F210 -> 51 | H210: =G210 * 7.2 -> 367.2 | I210: =IF(B210="Yes", 100, 40) -> 40 | J210: =IF(C210>30,I210*0.15,IF(D210>5,IF(B210="YES",24,12),I210)) -> 6 | K210: =I210-J210 -> 34 | L210: =K210 * 4 -> 136 | M210: Extreme Heat | N210: 2026 | O210: May
A211: 46169 | B211: =IF( WEEKDAY(A211, 2) > 5, "YES", "NO") -> NO | C211: =_xlfn.XLOOKUP(A211,Weather_clean_data!A:A,Weather_clean_data!B:B,0) -> 29 | D211: =_xlfn.XLOOKUP(A211, Weather_clean_data!A:A, Weather_clean_data!C:C, 0) -> 4.5 | E211: =IF(B211="Yes", 150, 60) -> 60 | F211: =IF(C211>30,E211*0.15,IF(D211>5,IF(B211="YES",36,18),E211)) -> 60 | G211: =E211-F211 -> 0 | H211: =G211 * 7.2 -> 0 | I211: =IF(B211="Yes", 100, 40) -> 40 | J211: =IF(C211>30,I211*0.15,IF(D211>5,IF(B211="YES",24,12),I211)) -> 40 | K211: =I211-J211 -> 0 | L211: =K211 * 4 -> 0 | M211: Normal Weekday | N211: 2026 | O211: May
A212: 46170 | B212: =IF( WEEKDAY(A212, 2) > 5, "YES", "NO") -> NO | C212: =_xlfn.XLOOKUP(A212,Weather_clean_data!A:A,Weather_clean_data!B:B,0) -> 30 | D212: =_xlfn.XLOOKUP(A212, Weather_clean_data!A:A, Weather_clean_data!C:C, 0) -> 0.5 | E212: =IF(B212="Yes", 150, 60) -> 60 | F212: =IF(C212>30,E212*0.15,IF(D212>5,IF(B212="YES",36,18),E212)) -> 60 | G212: =E212-F212 -> 0 | H212: =G212 * 7.2 -> 0 | I212: =IF(B212="Yes", 100, 40) -> 40 | J212: =IF(C212>30,I212*0.15,IF(D212>5,IF(B212="YES",24,12),I212)) -> 40 | K212: =I212-J212 -> 0 | L212: =K212 * 4 -> 0 | M212: Normal Weekday | N212: 2026 | O212: May
A213: 46171 | B213: =IF( WEEKDAY(A213, 2) > 5, "YES", "NO") -> NO | C213: =_xlfn.XLOOKUP(A213,Weather_clean_data!A:A,Weather_clean_data!B:B,0) -> 24 | D213: =_xlfn.XLOOKUP(A213, Weather_clean_data!A:A, Weather_clean_data!C:C, 0) -> 0.3 | E213: =IF(B213="Yes", 150, 60) -> 60 | F213: =IF(C213>30,E213*0.15,IF(D213>5,IF(B213="YES",36,18),E213)) -> 60 | G213: =E213-F213 -> 0 | H213: =G213 * 7.2 -> 0 | I213: =IF(B213="Yes", 100, 40) -> 40 | J213: =IF(C213>30,I213*0.15,IF(D213>5,IF(B213="YES",24,12),I213)) -> 40 | K213: =I213-J213 -> 0 | L213: =K213 * 4 -> 0 | M213: Ideal BBQ Day | N213: 2026 | O213: May
A214: 46172 | B214: =IF( WEEKDAY(A214, 2) > 5, "YES", "NO") -> YES | C214: =_xlfn.XLOOKUP(A214,Weather_clean_data!A:A,Weather_clean_data!B:B,0) -> 25 | D214: =_xlfn.XLOOKUP(A214, Weather_clean_data!A:A, Weather_clean_data!C:C, 0) -> 0 | E214: =IF(B214="Yes", 150, 60) -> 150 | F214: =IF(C214>30,E214*0.15,IF(D214>5,IF(B214="YES",36,18),E214)) -> 150 | G214: =E214-F214 -> 0 | H214: =G214 * 7.2 -> 0 | I214: =IF(B214="Yes", 100, 40) -> 100 | J214: =IF(C214>30,I214*0.15,IF(D214>5,IF(B214="YES",24,12),I214)) -> 100 | K214: =I214-J214 -> 0 | L214: =K214 * 4 -> 0 | M214: Ideal BBQ Day | N214: 2026 | O214: May
A215: 46173 | B215: =IF( WEEKDAY(A215, 2) > 5, "YES", "NO") -> YES | C215: =_xlfn.XLOOKUP(A215,Weather_clean_data!A:A,Weather_clean_data!B:B,0) -> 20 | D215: =_xlfn.XLOOKUP(A215, Weather_clean_data!A:A, Weather_clean_data!C:C, 0) -> 0 | E215: =IF(B215="Yes", 150, 60) -> 150 | F215: =IF(C215>30,E215*0.15,IF(D215>5,IF(B215="YES",36,18),E215)) -> 150 | G215: =E215-F215 -> 0 | H215: =G215 * 7.2 -> 0 | I215: =IF(B215="Yes", 100, 40) -> 100 | J215: =IF(C215>30,I215*0.15,IF(D215>5,IF(B215="YES",24,12),I215)) -> 100 | K215: =I215-J215 -> 0 | L215: =K215 * 4 -> 0 | M215: Ideal BBQ Day | N215: 2026 | O215: May
A216: 46174 | B216: =IF( WEEKDAY(A216, 2) > 5, "YES", "NO") -> NO | C216: =_xlfn.XLOOKUP(A216,Weather_clean_data!A:A,Weather_clean_data!B:B,0) -> 19 | D216: =_xlfn.XLOOKUP(A216, Weather_clean_data!A:A, Weather_clean_data!C:C, 0) -> 5.3 | E216: =IF(B216="Yes", 150, 60) -> 60 | F216: =IF(C216>30,E216*0.15,IF(D216>5,IF(B216="YES",36,18),E216)) -> 18 | G216: =E216-F216 -> 42 | H216: =G216 * 7.2 -> 302.4 | I216: =IF(B216="Yes", 100, 40) -> 40 | J216: =IF(C216>30,I216*0.15,IF(D216>5,IF(B216="YES",24,12),I216)) -> 12 | K216: =I216-J216 -> 28 | L216: =K216 * 4 -> 112 | M216: Heavy Rain | N216: 2026 | O216: June
A217: 46175 | B217: =IF( WEEKDAY(A217, 2) > 5, "YES", "NO") -> NO | C217: =_xlfn.XLOOKUP(A217,Weather_clean_data!A:A,Weather_clean_data!B:B,0) -> 19 | D217: =_xlfn.XLOOKUP(A217, Weather_clean_data!A:A, Weather_clean_data!C:C, 0) -> 7 | E217: =IF(B217="Yes", 150, 60) -> 60 | F217: =IF(C217>30,E217*0.15,IF(D217>5,IF(B217="YES",36,18),E217)) -> 18 | G217: =E217-F217 -> 42 | H217: =G217 * 7.2 -> 302.4 | I217: =IF(B217="Yes", 100, 40) -> 40 | J217: =IF(C217>30,I217*0.15,IF(D217>5,IF(B217="YES",24,12),I217)) -> 12 | K217: =I217-J217 -> 28 | L217: =K217 * 4 -> 112 | M217: Heavy Rain | N217: 2026 | O217: June
A218: 46176 | B218: =IF( WEEKDAY(A218, 2) > 5, "YES", "NO") -> NO | C218: =_xlfn.XLOOKUP(A218,Weather_clean_data!A:A,Weather_clean_data!B:B,0) -> 20 | D218: =_xlfn.XLOOKUP(A218, Weather_clean_data!A:A, Weather_clean_data!C:C, 0) -> 2.6 | E218: =IF(B218="Yes", 150, 60) -> 60 | F218: =IF(C218>30,E218*0.15,IF(D218>5,IF(B218="YES",36,18),E218)) -> 60 | G218: =E218-F218 -> 0 | H218: =G218 * 7.2 -> 0 | I218: =IF(B218="Yes", 100, 40) -> 40 | J218: =IF(C218>30,I218*0.15,IF(D218>5,IF(B218="YES",24,12),I218)) -> 40 | K218: =I218-J218 -> 0 | L218: =K218 * 4 -> 0 | M218: Normal Weekday | N218: 2026 | O218: June
A219: 46177 | B219: =IF( WEEKDAY(A219, 2) > 5, "YES", "NO") -> NO | C219: =_xlfn.XLOOKUP(A219,Weather_clean_data!A:A,Weather_clean_data!B:B,0) -> 17.2 | D219: =_xlfn.XLOOKUP(A219, Weather_clean_data!A:A, Weather_clean_data!C:C, 0) -> 2.2 | E219: =IF(B219="Yes", 150, 60) -> 60 | F219: =IF(C219>30,E219*0.15,IF(D219>5,IF(B219="YES",36,18),E219)) -> 60 | G219: =E219-F219 -> 0 | H219: =G219 * 7.2 -> 0 | I219: =IF(B219="Yes", 100, 40) -> 40 | J219: =IF(C219>30,I219*0.15,IF(D219>5,IF(B219="YES",24,12),I219)) -> 40 | K219: =I219-J219 -> 0 | L219: =K219 * 4 -> 0 | M219: Normal Weekday | N219: 2026 | O219: June
A220: 46178 | B220: =IF( WEEKDAY(A220, 2) > 5, "YES", "NO") -> NO | C220: =_xlfn.XLOOKUP(A220,Weather_clean_data!A:A,Weather_clean_data!B:B,0) -> 16 | D220: =_xlfn.XLOOKUP(A220, Weather_clean_data!A:A, Weather_clean_data!C:C, 0) -> 0 | E220: =IF(B220="Yes", 150, 60) -> 60 | F220: =IF(C220>30,E220*0.15,IF(D220>5,IF(B220="YES",36,18),E220)) -> 60 | G220: =E220-F220 -> 0 | H220: =G220 * 7.2 -> 0 | I220: =IF(B220="Yes", 100, 40) -> 40 | J220: =IF(C220>30,I220*0.15,IF(D220>5,IF(B220="YES",24,12),I220)) -> 40 | K220: =I220-J220 -> 0 | L220: =K220 * 4 -> 0 | M220: Ideal BBQ Day | N220: 2026 | O220: June
A221: 46179 | B221: =IF( WEEKDAY(A221, 2) > 5, "YES", "NO") -> YES | C221: =_xlfn.XLOOKUP(A221,Weather_clean_data!A:A,Weather_clean_data!B:B,0) -> 18 | D221: =_xlfn.XLOOKUP(A221, Weather_clean_data!A:A, Weather_clean_data!C:C, 0) -> 7.4 | E221: =IF(B221="Yes", 150, 60) -> 150 | F221: =IF(C221>30,E221*0.15,IF(D221>5,IF(B221="YES",36,18),E221)) -> 36 | G221: =E221-F221 -> 114 | H221: =G221 * 7.2 -> 820.8 | I221: =IF(B221="Yes", 100, 40) -> 100 | J221: =IF(C221>30,I221*0.15,IF(D221>5,IF(B221="YES",24,12),I221)) -> 24 | K221: =I221-J221 -> 76 | L221: =K221 * 4 -> 304 | M221: Heavy Rain | N221: 2026 | O221: June
... A239: 46197 | B239: =IF( WEEKDAY(A239, 2) > 5, "YES", "NO") -> NO | C239: =_xlfn.XLOOKUP(A239,Weather_clean_data!A:A,Weather_clean_data!B:B,0) -> 35.3 | D239: =_xlfn.XLOOKUP(A239, Weather_clean_data!A:A, Weather_clean_data!C:C, 0) -> 0 | E239: =IF(B239="Yes", 150, 60) -> 60 | F239: =IF(C239>30,E239*0.15,IF(D239>5,IF(B239="YES",36,18),E239)) -> 9 | G239: =E239-F239 -> 51 | H239: =G239 * 7.2 -> 367.2 | I239: =IF(B239="Yes", 100, 40) -> 40 | J239: =IF(C239>30,I239*0.15,IF(D239>5,IF(B239="YES",24,12),I239)) -> 6 | K239: =I239-J239 -> 34 | L239: =K239 * 4 -> 136 | M239: Extreme Heat | N239: 2026 | O239: June
A240: 46198 | B240: =IF( WEEKDAY(A240, 2) > 5, "YES", "NO") -> NO | C240: 34.2 | D240: =_xlfn.XLOOKUP(A240, Weather_clean_data!A:A, Weather_clean_data!C:C, 0) -> 0 | E240: =IF(B240="Yes", 150, 60) -> 60 | F240: =IF(C240>30,E240*0.15,IF(D240>5,IF(B240="YES",36,18),E240)) -> 9 | G240: =E240-F240 -> 51 | H240: =G240 * 7.2 -> 367.2 | I240: =IF(B240="Yes", 100, 40) -> 40 | J240: =IF(C240>30,I240*0.15,IF(D240>5,IF(B240="YES",24,12),I240)) -> 6 | K240: =I240-J240 -> 34 | L240: =K240 * 4 -> 136 | M240: Normal Weekday | N240: 2026 | O240: June
A241: 46199 | B241: =IF( WEEKDAY(A241, 2) > 5, "YES", "NO") -> NO | C241: 28.7 | D241: 2.1 | E241: =IF(B241="Yes", 150, 60) -> 60 | F241: =IF(C241>30,E241*0.15,IF(D241>5,IF(B241="YES",36,18),E241)) -> 60 | G241: =E241-F241 -> 0 | H241: =G241 * 7.2 -> 0 | I241: =IF(B241="Yes", 100, 40) -> 40 | J241: =IF(C241>30,I241*0.15,IF(D241>5,IF(B241="YES",24,12),I241)) -> 40 | K241: =I241-J241 -> 0 | L241: =K241 * 4 -> 0 | M241: Ideal BBQ Day | N241: 2026 | O241: June
A242: 46200 | B242: =IF( WEEKDAY(A242, 2) > 5, "YES", "NO") -> YES | C242: 27.2 | D242: 1.2 | E242: =IF(B242="Yes", 150, 60) -> 150 | F242: =IF(C242>30,E242*0.15,IF(D242>5,IF(B242="YES",36,18),E242)) -> 150 | G242: =E242-F242 -> 0 | H242: =G242 * 7.2 -> 0 | I242: =IF(B242="Yes", 100, 40) -> 100 | J242: =IF(C242>30,I242*0.15,IF(D242>5,IF(B242="YES",24,12),I242)) -> 100 | K242: =I242-J242 -> 0 | L242: =K242 * 4 -> 0 | M242: Ideal BBQ Day | N242: 2026 | O242: June
A243: 46201 | B243: =IF( WEEKDAY(A243, 2) > 5, "YES", "NO") -> YES | C243: 21.4 | D243: 3.1 | E243: =IF(B243="Yes", 150, 60) -> 150 | F243: =IF(C243>30,E243*0.15,IF(D243>5,IF(B243="YES",36,18),E243)) -> 150 | G243: =E243-F243 -> 0 | H243: =G243 * 7.2 -> 0 | I243: =IF(B243="Yes", 100, 40) -> 100 | J243: =IF(C243>30,I243*0.15,IF(D243>5,IF(B243="YES",24,12),I243)) -> 100 | K243: =I243-J243 -> 0 | L243: =K243 * 4 -> 0 | M243: Ideal BBQ Day | N243: 2026 | O243: June
A244: 46202 | B244: =IF( WEEKDAY(A244, 2) > 5, "YES", "NO") -> NO | C244: 21.2 | D244: =_xlfn.XLOOKUP(A244, Weather_clean_data!A:A, Weather_clean_data!C:C, 0) -> 0 | E244: =IF(B244="Yes", 150, 60) -> 60 | F244: =IF(C244>30,E244*0.15,IF(D244>5,IF(B244="YES",36,18),E244)) -> 60 | G244: =E244-F244 -> 0 | H244: =G244 * 7.2 -> 0 | I244: =IF(B244="Yes", 100, 40) -> 40 | J244: =IF(C244>30,I244*0.15,IF(D244>5,IF(B244="YES",24,12),I244)) -> 40 | K244: =I244-J244 -> 0 | L244: =K244 * 4 -> 0 | M244: Normal Weekday | N244: 2026 | O244: June
A245: 46203 | B245: =IF( WEEKDAY(A245, 2) > 5, "YES", "NO") -> NO | C245: 21.6 | D245: =_xlfn.XLOOKUP(A245, Weather_clean_data!A:A, Weather_clean_data!C:C, 0) -> 0 | E245: =IF(B245="Yes", 150, 60) -> 60 | F245: =IF(C245>30,E245*0.15,IF(D245>5,IF(B245="YES",36,18),E245)) -> 60 | G245: =E245-F245 -> 0 | H245: =G245 * 7.2 -> 0 | I245: =IF(B245="Yes", 100, 40) -> 40 | J245: =IF(C245>30,I245*0.15,IF(D245>5,IF(B245="YES",24,12),I245)) -> 40 | K245: =I245-J245 -> 0 | L245: =K245 * 4 -> 0 | M245: Normal Weekday | N245: 2026 | O245: June

Sheet Weather_clean_data
A1: Date | B1: tmax | C1: prcp
A2: 45047 | B2: 18 | C2: 1.3
A3: 45048 | B3: 17 | C3: 0.1
A4: 45049 | B4: 16 | C4: 0
A5: 45050 | B5: 18 | C5: 1.9
A6: 45051 | B6: 18 | C6: 2.5
A7: 45052 | B7: 16 | C7: 2.3
A8: 45053 | B8: 19 | C8: 0
A9: 45054 | B9: 16 | C9: 9.3
A10: 45055 | B10: 18 | C10: 10.2
A11: 45056 | B11: 16 | C11: 3.2
A12: 45057 | B12: 19 | C12: 0.4
A13: 45058 | B13: 15 | C13: 0.1
... A239: 46197 | B239: 35.3 | C239: 0
A240: 46198
A241: 46199
A242: 46200
A243: 46201
A244: 46202
A245: 46203

Sheet Calculations
A1: Row Labels | B1: Sum of Beef_Financial_Loss_£ | C1: Sum of Pork_Financial_Loss_£
A2: Extreme Heat | B2: 3672 | C2: 1360
A3: Heavy Rain | B3: 9374.4 | C3: 3472
A4: Ideal BBQ Day | B4: 0 | C4: 0
A5: Normal Weekday | B5: 367.2 | C5: 136
A6: Grand Total | B6: 13413.6 | C6: 4968
A10: Row Labels | B10: Average of Beef_Financial_Loss_£ | C10: Average of Pork_Financial_Loss_£
A11: Extreme Heat | B11: 524.57143 | C11: 194.28571
A12: Heavy Rain | B12: 493.38947 | C12: 182.73684
A13: Ideal BBQ Day | B13: 0 | C13: 0
A14: Normal Weekday | B14: 3.1930435 | C14: 1.1826087
A15: Grand Total | B15: 54.97377 | C15: 20.360656
A19: Sum. Beef&Pork (Extreme Heat) | B19: Sum. Beef&Pork (Heavy Rain) | C19: Sum. Beef&Pork (Standart Weekend)
A20: =GETPIVOTDATA("Average of Beef_Financial_Loss_£",Calculations!$A$10,"Weather_Condition","Extreme Heat")+GETPIVOTDATA("Average of Pork_Financial_Loss_£",Calculations!$A$10,"Weather_Condition","Extreme Heat") -> 718.85714 | B20: =GETPIVOTDATA("Average of Beef_Financial_Loss_£",Calculations!$A$10,"Weather_Condition","Heavy Rain")+GETPIVOTDATA("Average of Pork_Financial_Loss_£",Calculations!$A$10,"Weather_Condition","Heavy Rain") -> 676.12632 | C20: =IFERROR(GETPIVOTDATA("Average of Beef_Financial_Loss_£",'Performance Dashboard'!$A$60,"Weather_Condition","Normal Weekday")+GETPIVOTDATA("Average of Pork_Financial_Loss_£",'Performance Dashboard'!$A$60,"Weather_Condition","Normal Weekday"), 0) -> 0
A24: Category | B24: Demand Change (Extreme Heat) | C24: Business Action
A25: Beef & Pork | B25: -0.85 | C25: Reduce purchases, protect the margin
A26: Soft Drinks | B26: 2.4 | C26: Increase the facing on the shelves
A27: Ice Cream | B27: 3.1 | C27: Urgently check the freezers
A28: Bagged Ice | B28: 4.5 | C28: Maximum delivery priority
A33: Total Heatwave Loss | B33: 5032
A34: Prevented Loss | B34: =B33 * 0.85 -> 4277.2
A35: Remaining Loss | B35: =B33 * 0.15 -> 754.8
A38: Sourcing Strategy | B38: Financial Impact (£) | C38: Type
A39: Traditional Sourcing (Blind) | B39: =B33 -> 5032 | C39: Real Loss
A40: Smart Sourcing (With Forecast) | B40: =B35 -> 754.8 | C40: Remaining Risk
A41: Net Savings (Твоя аналітика) | B41: =B34 -> 4277.2 | C41: Money Saved

Sheet Performance Dashboard
